{
    "nodes": [
        {
            "type": "PPMChannelNode",
            "x": 800.0,
            "y": 820.0,
            "title": "PPM Channel 8"
        },
        {
            "type": "PPMChannelNode",
            "x": 800.0,
            "y": 710.0,
            "title": "PPM Channel 7"
        },
        {
            "type": "PPMChannelNode",
            "x": 800.0,
            "y": 600.0,
            "title": "PPM Channel 6"
        },
        {
            "type": "PPMChannelNode",
            "x": 800.0,
            "y": 490.0,
            "title": "PPM Channel 5"
        },
        {
            "type": "PPMChannelNode",
            "x": 800.0,
            "y": 380.0,
            "title": "PPM Channel 4"
        },
        {
            "type": "PPMChannelNode",
            "x": 800.0,
            "y": 270.0,
            "title": "PPM Channel 3"
        },
        {
            "type": "PPMChannelNode",
            "x": 800.0,
            "y": 160.0,
            "title": "PPM Channel 2"
        },
        {
            "type": "PPMChannelNode",
            "x": 800.0,
            "y": 50.0,
            "title": "PPM Channel 1"
        },
        {
            "type": "JoystickNode",
            "x": 50.0,
            "y": 50.0,
            "title": "Logitech Extreme 3D"
        }
    ],
    "connections": []
}